redismpx/__init__.py
redismpx/channel.py
redismpx/multiplexer.py
redismpx/pattern.py
redismpx/promise.py
redismpx/utils.py
redismpx/internal/__init__.py
redismpx/internal/connection.py
redismpx/internal/list.py
redismpx-0.5.2.dist-info/LICENSE
redismpx-0.5.2.dist-info/METADATA
redismpx-0.5.2.dist-info/WHEEL
redismpx-0.5.2.dist-info/top_level.txt
redismpx-0.5.2.dist-info/RECORD
