Metadata-Version: 2.1
Name: redismpx
Version: 0.5.2
Summary: A Redis Pub/Sub multiplexer.
Home-page: https://github.com/RedisMPX/python-mpx
Author: Loris Cro
Author-email: kappaloris@gmail.com
License: UNKNOWN
Platform: UNKNOWN
Classifier: Programming Language :: Python :: 3
Classifier: License :: OSI Approved :: MIT License
Classifier: Operating System :: OS Independent
Requires-Python: >=3.7
Requires-Dist: aioredis
